file_archive/__init__.py
file_archive/__main__.py
file_archive/compat.py
file_archive/database.py
file_archive/entry_point.py
file_archive/errors.py
file_archive/main.py
file_archive/parser.py
file_archive/trans.py
file_archive/viewer.py
file_archive/l10n/fr_FR/LC_MESSAGES/file_archive.mo
file_archive-0.6.dist-info/zip-safe
file_archive-0.6.dist-info/top_level.txt
file_archive-0.6.dist-info/METADATA
file_archive-0.6.dist-info/entry_points.txt
file_archive-0.6.dist-info/DESCRIPTION.rst
file_archive-0.6.dist-info/metadata.json
file_archive-0.6.dist-info/WHEEL
file_archive-0.6.dist-info/RECORD
