Metadata-Version: 2.0
Name: file-archive
Version: 0.6
Summary: A file store with searchable metadata
Home-page: http://github.com/remram44/file_archive
Author: Remi Rampin
Author-email: vistrails-dev@vistrails.org
License: Modified BSD License
Keywords: file,archive,metadata,vida,nyu
Platform: UNKNOWN
Classifier: Development Status :: 3 - Alpha
Classifier: License :: OSI Approved :: BSD License
Classifier: Programming Language :: Python :: 2
Classifier: Programming Language :: Python :: 3
Classifier: Environment :: Console
Classifier: Operating System :: OS Independent
Classifier: Intended Audience :: Developers
Classifier: Intended Audience :: Science/Research
Classifier: Topic :: System :: Archiving
Requires-Dist: tdparser (>=1.1.4)
